{
  "neoforge:conditions": [
    {
      "type": "neoforge:mod_loaded",
      "modid": "mcwfurnitures"
    },
    {
      "type": "neoforge:mod_loaded",
      "modid": "environmental"
    }
  ],
  "type": "minecraft:crafting_shaped",
  "category": "building",
  "group": "stool_chair",
  "key": {
    "A": {
      "item": "environmental:stripped_wisteria_log"
    },
    "B": {
      "item": "environmental:wisteria_fence"
    }
  },
  "pattern": [
    "A",
    "A",
    "B"
  ],
  "result": {
    "count": 1,
    "id": "mcwabnormals:stripped_wisteria_stool_chair"
  }
}