{
"conditions": [
    {
      "type": "forge:mod_loaded",
      "modid": "mcwstairs"
    },
    {
      "type": "forge:mod_loaded",
      "modid": "atmospheric"
    }
  ],
  "type" : "minecraft:crafting_shaped",
  "group" : "terrace_stairs",
  "pattern" : [ "W  ", "ZW ", " ZW" ],
  "key" : {
    "W" : {
      "item" : "atmospheric:stripped_kousa_log"
    },
    "Z" : {
      "item" : "atmospheric:kousa_log"
    }
  },
  "result" : {
    "item" : "mcwabnormals:kousa_terrace_stairs",
    "count" : 5
  }
}
