{
  "type": "forge:conditional",
  "recipes": [
    {
      "conditions": [
        {
          "type": "forge:mod_loaded",
          "modid": "mcwfurnitures"
        },
        {
          "type": "forge:mod_loaded",
          "modid": "atmospheric"
        }
      ],
      "recipe": {
        "type": "minecraft:crafting_shaped",
        "category": "building",
        "group": "chairs",
        "key": {
          "A": {
            "item": "atmospheric:aspen_log"
          },
          "B": {
            "item": "atmospheric:aspen_slab"
          },
          "C": {
            "item": "atmospheric:aspen_fence"
          }
        },
        "pattern": [
          " A",
          "BA",
          "CC"
        ],
        "result": {
          "item": "mcwabnormals:aspen_chair"
        },
        "show_notification": true
      }
    }
  ]
}