{
"neoforge:conditions": [
    {
      "type": "neoforge:mod_loaded",
      "modid": "mcwfences"
    },
    {
      "type": "neoforge:mod_loaded",
      "modid": "environmental"
    }
  ],  "parent": "minecraft:recipes/root",
  "rewards": {
    "recipes": [
	"mcwabnormals:purple_wisteria_hedge"
    ]
  },
  "criteria": {
    "has_birch": {
      "trigger": "minecraft:inventory_changed",
      "conditions": {
        "items": [
          {
            "item": "environmental:purple_wisteria_leaves"
          }
        ]
      }
    }
  },
  "requirements": [
    [
      "has_birch"
    ]
  ]
}
