{
"forge:conditional": [
    {
      "forge:condition": {
        "type": "forge:and",
        "values": [
          {
            "type": "forge:mod_loaded",
            "modid": "mcwbridges"
          },
          {
            "type": "forge:mod_loaded",
            "modid": "biomeswevegone"
          }
        ]
      },
  "type" : "minecraft:crafting_shaped",
  "group" : "stone_piers",
  "pattern" : [ "WFW" ],
  "key" : {
    "F" : "biomeswevegone:purple_sandstone_wall",
    "W" : "biomeswevegone:purple_sandstone"
  },
  "result" : {
    "count" : 3,
    "id" : "mcwbyg:purple_sandstone_bridge_pier"
  }
}
  ]
}
