{
"forge:conditional": [
    {
      "forge:condition": {
        "type": "forge:and",
        "values": [
          {
            "type": "forge:mod_loaded",
            "modid": "mcwfurnitures"
          },
          {
            "type": "forge:mod_loaded",
            "modid": "biomeswevegone"
          }
        ]
      },
  "type" : "minecraft:crafting_shaped",
  "group" : "end_table",
  "pattern" : [ "A", "B" ],
  "key" : {
    "A" : "mcwbyg:willow_table",
    "B" : "biomeswevegone:willow_log"
  },
  "result" : {
    "count" : 1,
    "id" : "mcwbyg:willow_end_table"
  }
}
  ]
}
