{
  "type": "forge:conditional",
  "recipes": [
    {
      "conditions": [
        {
          "type": "forge:mod_loaded",
          "modid": "mcwfurnitures"
        },
        {
          "type": "forge:mod_loaded",
          "modid": "quark"
        }
      ],
      "recipe": {
        "type": "minecraft:crafting_shaped",
        "group": "bookshelves",
        "key": {
          "A": {
            "item": "quark:ancient_log"
          },
          "B": {
            "item": "minecraft:book"
          }
        },
        "pattern": [
          "AAA",
          "BBB",
          "AAA"
        ],
        "result": {
          "count": 4,
          "item": "mcwquark:ancient_bookshelf"
        }
      }
    }
  ]
}