{
  "neoforge:conditions": [
    {
      "type": "neoforge:mod_loaded",
      "modid": "mcwfurnitures"
    },
    {
      "type": "neoforge:mod_loaded",
      "modid": "premium_wood"
    }
  ],
  "type": "minecraft:crafting_shaped",
  "category": "building",
  "group": "kitchen_cabinet",
  "key": {
    "A": "premium_wood:maple_log",
    "B": "mcwfurnitures:cabinet_door"
  },
  "pattern": [
    "AA",
    "AB",
    "AA"
  ],
  "result": {
    "count": 4,
    "id": "mcwmoddinglegacy:pwood_maple_kitchen_cabinet"
  }
}