{
  "neoforge:conditions": [
    {
      "type": "neoforge:mod_loaded",
      "modid": "mcwtrpdoors"
    },
    {
      "type": "neoforge:mod_loaded",
      "modid": "biomesoplenty"
    }
  ],
  "parent": "minecraft:recipes/root",
  "criteria": {
    "has_the_recipe": {
      "conditions": {
        "recipe": "mcwbiomesoplenty:willow_whispering_trapdoor"
      },
      "trigger": "minecraft:recipe_unlocked"
    },
    "has_willow_planks": {
      "conditions": {
        "items": [
          {
            "items": "biomesoplenty:willow_planks"
          }
        ]
      },
      "trigger": "minecraft:inventory_changed"
    }
  },
  "requirements": [
    [
      "has_the_recipe",
      "has_willow_planks"
    ]
  ],
  "rewards": {
    "recipes": [
      "mcwbiomesoplenty:willow_whispering_trapdoor"
    ]
  }
}