{
"conditions": [
    {
      "type": "forge:mod_loaded",
      "modid": "mcwfences"
    },
    {
      "type": "forge:mod_loaded",
      "modid": "biomeswevegone"
    }
  ],
    "type": "minecraft:crafting_shaped",
	"group": "highley",
    
    "pattern":
    [
		"ABA",
		"ABA"
    ],
    
    "key":
    { 
        "A":
        {
            "item": "minecraft:stick"
        },    
        
        "B":
        {
            "item": "biomeswevegone:redwood_log"
        }
    },
    
    "result":
    {
        "item":  "mcwbyg:redwood_highley_gate",
        "count": 1
    }
}


