{
  "advancements": [
    {
      "conditions": [
        {
          "modid": "mcwfences",
          "type": "forge:mod_loaded"
        },
        {
          "modid": "cinderscapes",
          "type": "forge:mod_loaded"
        }
      ],
      "advancement": {
        "parent": "minecraft:recipes/root",
        "rewards": {
          "recipes": [
            "mcwterraformersmc:rose_quartz_bricks_grass_topped_wall"
          ]
        },
        "criteria": {
          "has_rose_quartz_bricks": {
            "trigger": "minecraft:inventory_changed",
            "conditions": {
              "items": [
                {
                  "items": [
                    "cinderscapes:rose_quartz_bricks"
                  ]
                }
              ]
            }
          },
          "has_the_recipe": {
            "trigger": "minecraft:recipe_unlocked",
            "conditions": {
              "recipe": "mcwterraformersmc:rose_quartz_bricks_grass_topped_wall"
            }
          }
        },
        "requirements": [
          [
            "has_rose_quartz_bricks",
            "has_the_recipe"
          ]
        ]
      }
    }
  ]
}