{
"forge:conditional": [
    {
      "forge:condition": {
        "type": "forge:and",
        "values": [
          {
            "type": "forge:mod_loaded",
            "modid": "mcwstairs"
          },
          {
            "type": "forge:mod_loaded",
            "modid": "biomesoplenty"
          }
        ]
      },
  "type" : "minecraft:crafting_shaped",
  "group" : "mcwstairs_railing",
  "pattern" : [ "W  ", "WW ", "WWW" ],
  "key" : {
    "W" : "mcwbiomesoplenty:willow_balcony"
  },
  "result" : {
    "count" : 6,
    "id" : "mcwbiomesoplenty:willow_railing"
  }
}
  ]
}
