{
  "fabric:load_conditions": [
    {
      "condition": "fabric:all_mods_loaded",
      "values": [
        "cinderscapes",
        "mcwbridges"
      ]
    }
  ],
  "type": "minecraft:crafting_shaped",
  "category": "building",
  "group": "stone_bridges",
  "key": {
    "A": {
      "item": "cinderscapes:smoky_quartz_slab"
    },
    "B": {
      "item": "cinderscapes:smoky_quartz_pillar"
    }
  },
  "pattern": [
    "B B",
    "AAA"
  ],
  "result": {
    "count": 4,
    "item": "mcwterraformersmc:smoky_quartz_bricks_bridge"
  },
  "show_notification": true
}