{
  "type": "forge:conditional",
  "recipes": [
    {
      "conditions": [
        {
          "type": "forge:mod_loaded",
          "modid": "mcwfences"
        },
        {
          "type": "forge:mod_loaded",
          "modid": "regions_unexplored"
        }
      ],
      "recipe": {
        "type": "minecraft:crafting_shaped",
        "group": "picket",
        "key": {
          "A": {
            "item": "minecraft:stick"
          },
          "B": {
            "item": "regions_unexplored:pine_planks"
          },
          "C": {
            "item": "regions_unexplored:pine_log"
          }
        },
        "pattern": [
          "CBC",
          "CAC"
        ],
        "result": {
          "count": 3,
          "item": "mcwregionsunexplored:pine_picket_fence"
        }
      }
    }
  ]
}