{
  "advancements": [
    {
      "advancement": {
        "parent": "minecraft:recipes/root",
        "criteria": {
          "has_fir_log": {
            "conditions": {
              "items": [
                {
                  "items": [
                    "biomeswevegone:fir_log"
                  ]
                }
              ]
            },
            "trigger": "minecraft:inventory_changed"
          },
          "has_the_recipe": {
            "conditions": {
              "recipe": "mcwbyg:fir_beach_door"
            },
            "trigger": "minecraft:recipe_unlocked"
          }
        },
        "requirements": [
          [
            "has_fir_log",
            "has_the_recipe"
          ]
        ],
        "rewards": {
          "recipes": [
            "mcwbyg:fir_beach_door"
          ]
        },
        "sends_telemetry_event": false
      },
      "conditions": [
        {
          "type": "forge:mod_loaded",
          "modid": "mcwdoors"
        },
        {
          "type": "forge:mod_loaded",
          "modid": "biomeswevegone"
        }
      ]
    }
  ]
}