{
  "fabric:load_conditions": [
    {
      "condition": "fabric:all_mods_loaded",
      "values": [
        "regions_unexplored",
        "mcwfences"
      ]
    }
  ],
  "type": "minecraft:crafting_shaped",
  "category": "building",
  "group": "stockade",
  "key": {
    "A": {
      "item": "regions_unexplored:cherry_log"
    },
    "B": {
      "item": "regions_unexplored:cherry_planks"
    }
  },
  "pattern": [
    "ABA",
    "BAB"
  ],
  "result": {
    "count": 3,
    "item": "mcwregionsunexplored:cherry_stockade_fence"
  }
}