{
  "type": "minecraft:crafting_shapeless",
  "group": "shutters",
  "ingredients": [
    {
      "item": "terrestria:rainbow_eucalyptus_trapdoor"
    },
    {
      "item": "terrestria:rainbow_eucalyptus_trapdoor"
    },
    {
      "item": "terrestria:rainbow_eucalyptus_trapdoor"
    }
  ],
  "result": {
    "item": "mcwterraformersmc:rainbow_eucalyptus_shutter",
    "count": 3
  },
  "fabric:load_conditions": [
    {
      "condition": "fabric:all_mods_loaded",
      "values": [
        "terrestria",
        "mcwwindows"
      ]
    }
  ]
}