{
  "fabric:load_conditions": [
    {
      "condition": "fabric:all_mods_loaded",
      "values": [
        "mcwbridges",
        "terrestria"
      ]
    }
  ],
  "type": "minecraft:crafting_shaped",
  "category": "building",
  "group": "log_stairs",
  "key": {
    "A": {
      "item": "mcwterraformersmc:cypress_log_bridge_middle"
    }
  },
  "pattern": [
    "  A",
    " AA",
    "AAA"
  ],
  "result": {
    "count": 6,
    "item": "mcwterraformersmc:cypress_log_bridge_stair"
  },
  "show_notification": true
}