{
"neoforge:conditions": [
    {
      "type": "neoforge:mod_loaded",
      "modid": "mcwfurnitures"
    },
    {
      "type": "neoforge:mod_loaded",
      "modid": "environmental"
    }
  ],
  "type" : "minecraft:crafting_shaped",
  "group" : "glass_table",
  "pattern" : [ "A", "B" ],
  "key" : {
    "A" : {
      "item" : "mcwabnormals:stripped_wisteria_end_table"
    },
    "B" : {
      "item" : "minecraft:glass"
    }
  },
  "result" : {
    "count" : 1,
    "id" : "mcwabnormals:stripped_wisteria_glass_table"
  }
}
