{
"neoforge:conditions": [
    {
      "type": "neoforge:mod_loaded",
      "modid": "mcwbridges"
    },
    {
      "type": "neoforge:mod_loaded",
      "modid": "environmental"
    }
  ],
  "type" : "minecraft:crafting_shaped",
  "group" : "wooden_piers",
  "pattern" : [ "WFW" ],
  "key" : {
    "F" : {
      "item" : "environmental:willow_fence"
    },
    "W" : {
      "item" : "environmental:willow_log"
    }
  },
  "result" : {
    "count" : 3,
    "id" : "mcwabnormals:willow_bridge_pier"
  }
}
