{
  "advancements": [
    {
      "conditions": [
        {
          "modid": "mcwfences",
          "type": "forge:mod_loaded"
        },
        {
          "modid": "regions_unexplored",
          "type": "forge:mod_loaded"
        }
      ],
      "advancement": {
        "parent": "minecraft:recipes/root",
        "rewards": {
          "recipes": [
            "mcwregionsunexplored:larch_hedge"
          ]
        },
        "criteria": {
          "has_larch_leaves": {
            "trigger": "minecraft:inventory_changed",
            "conditions": {
              "items": [
                {
                  "items": [
                    "regions_unexplored:larch_leaves"
                  ]
                }
              ]
            }
          },
          "has_the_recipe": {
            "trigger": "minecraft:recipe_unlocked",
            "conditions": {
              "recipe": "mcwregionsunexplored:larch_hedge"
            }
          }
        },
        "requirements": [
          [
            "has_larch_leaves",
            "has_the_recipe"
          ]
        ]
      }
    }
  ]
}