{
  "neoforge:conditions": [
    {
      "type": "neoforge:and",
      "values": [
        {
          "type": "neoforge:mod_loaded",
          "modid": "mcwfurnitures"
        },
        {
          "type": "neoforge:mod_loaded",
          "modid": "nomansland"
        }
      ]
    }
  ],
  "type": "minecraft:crafting_shaped",
  "category": "building",
  "group": "stripped_stool_chairs",
  "key": {
    "A": {
      "item": "nomansland:stripped_maple_log"
    },
    "B": {
      "item": "nomansland:maple_fence"
    }
  },
  "pattern": [
    "A",
    "A",
    "B"
  ],
  "result": {
    "count": 1,
    "id": "mcwaurora:stripped_maple_stool_chair"
  }
}