{
  "type": "forge:conditional",
  "recipes": [
    {
      "conditions": [
        {
          "type": "forge:mod_loaded",
          "modid": "mcwfences"
        },
        {
          "type": "forge:mod_loaded",
          "modid": "biomeswevegone"
        }
      ],
      "recipe": {
        "type": "minecraft:crafting_shaped",
        "category": "building",
        "group": "curved_gate",
        "key": {
          "A": {
            "item": "biomeswevegone:zelkova_planks"
          },
          "B": {
            "item": "biomeswevegone:zelkova_log"
          }
        },
        "pattern": [
          "B A",
          "BAA"
        ],
        "result": {
          "count": 4,
          "item": "mcwbyg:zelkova_curved_gate"
        },
        "show_notification": true
      }
    }
  ]
}