{
  "parent": "minecraft:recipes/root",
  "rewards": {
    "recipes": [
	  "mcwaurora:redbud_bulk_stairs",
	  "mcwaurora:redbud_compact_stairs",
	  "mcwaurora:redbud_loft_stairs",
	  "mcwaurora:redbud_skyline_stairs",
	  "mcwaurora:redbud_terrace_stairs",
	  "mcwaurora:redbud_railing",
	  "mcwaurora:redbud_balcony",
	  "mcwaurora:redbud_platform"
    ]
  },
  "criteria": {
    "has_planks": {
      "trigger": "minecraft:inventory_changed",
      "conditions": {
        "items": [
          {
            "items": [
              "abundance:redbud_log"
            ]
          }
        ]
      }
    }
  },
  "requirements": [
    [
      "has_planks"
    ]
  ]
}
