{
"conditions": [
    {
      "type": "forge:mod_loaded",
      "modid": "mcwfurnitures"
    },
    {
      "type": "forge:mod_loaded",
      "modid": "biomeswevegone"
    }
  ],
    "type": "minecraft:crafting_shaped",
    "group": "double_drawer_counter",
    "pattern":
    [
        "A",
        "B"	
    ],
    
    "key":
    { 
	    "A":
        {
            "item": "biomeswevegone:redwood_slab"
        }, 
		
        "B":
        {
            "item": "mcwbyg:redwood_double_drawer"
        }
    },
    
    "result":
    {
        "item":  "mcwbyg:redwood_double_drawer_counter",
        "count": 1
    }
}


