{
  "parent": "minecraft:recipes/root",
  "rewards": {
    "recipes": [
      "mcwmoddinglegacy:bsky_bluebright_glass_trapdoor"
    ]
  },
  "criteria": {
    "has_logs": {
      "trigger": "minecraft:inventory_changed",
      "conditions": {
        "items": [
          {
            "items": 
			[ "blue_skies:bluebright_log"
                      ]
          }
        ]
      }
    },
    "has_the_recipe": {
      "trigger": "minecraft:recipe_unlocked",
      "conditions": {
        "recipe": "mcwmoddinglegacy:bsky_bluebright_glass_trapdoor"
      }
    }
  },
  "requirements": [
    [
      "has_logs",
      "has_the_recipe"
    ]
  ]
}
