{
  "type": "forge:conditional",
  "forge:condition": {
    "type": "forge:and",
    "values": [
      {
        "type": "forge:mod_loaded",
        "modid": "mcwfurnitures"
      },
      {
        "type": "forge:mod_loaded",
        "modid": "biomesoplenty"
      }
    ]
  },
  "recipes": [
    {
      "type": "minecraft:crafting_shaped",
      "category": "building",
      "group": "bookshelf_drawer",
      "key": {
        "A": {
          "item": "biomesoplenty:willow_log"
        },
        "B": {
          "item": "mcwfurnitures:cabinet_drawer"
        },
        "C": {
          "item": "minecraft:book"
        }
      },
      "pattern": [
        "AAA",
        "ABA",
        "ACA"
      ],
      "result": {
        "count": 4,
        "item": "mcwbiomesoplenty:willow_bookshelf_drawer"
      }
    }
  ]
}