{
  "type": "forge:conditional",
  "recipes": [
    {
      "conditions": [
        {
          "type": "forge:mod_loaded",
          "modid": "mcwfences"
        },
        {
          "type": "forge:mod_loaded",
          "modid": "blue_skies"
        }
      ],
      "recipe": {
        "type": "minecraft:crafting_shaped",
        "group": "wired",
        "key": {
          "A": {
            "item": "minecraft:stick"
          },
          "B": {
            "item": "blue_skies:dusk_log"
          },
          "C": {
            "item": "minecraft:iron_bars"
          }
        },
        "pattern": [
          "ACA",
          "ABA"
        ],
        "result": {
          "count": 3,
          "item": "mcwmoddinglegacy:bsky_dusk_wired_fence"
        }
      }
    }
  ]
}