{
"conditions": [
    {
      "type": "forge:mod_loaded",
      "modid": "mcwfurnitures"
    },
    {
      "type": "forge:mod_loaded",
      "modid": "terrestria"
    }
  ],
    "type": "minecraft:crafting_shaped",
    "group": "desk",
    "pattern":
    [
        "AAA",
        "B B"                
    ],
    
    "key":
    { 
	    "A":
        {
            "item": "terrestria:redwood_log"
        }, 
		
		
        "B":
        {
            "item": "terrestria:redwood_fence"
        }
    },
    
    "result":
    {
        "item":  "mcwterraformersmc:redwood_desk",
        "count": 2
    }
}


