{
"conditions": [
    {
      "type": "forge:mod_loaded",
      "modid": "mcwfences"
    },
    {
      "type": "forge:mod_loaded",
      "modid": "regions_unexplored"
    }
  ],  "parent": "minecraft:recipes/root",
  "rewards": {
    "recipes": [
	"mcwregionsunexplored:orange_maple_hedge"
    ]
  },
  "criteria": {
    "has_birch": {
      "trigger": "minecraft:inventory_changed",
      "conditions": {
        "items": [
          {
            "item": "regions_unexplored:orange_maple_leaves"
          }
        ]
      }
    }
  },
  "requirements": [
    [
      "has_birch"
    ]
  ]
}
