{
  "type": "forge:conditional",
  "recipes": [
    {
      "conditions": [
        {
          "type": "forge:mod_loaded",
          "modid": "mcwfurnitures"
        },
        {
          "type": "forge:mod_loaded",
          "modid": "byg"
        }
      ],
      "recipe": {
        "type": "minecraft:crafting_shaped",
        "group": "chairs",
        "key": {
          "A": {
            "item": "byg:sythian_stem"
          },
          "B": {
            "item": "byg:sythian_slab"
          },
          "C": {
            "item": "byg:sythian_fence"
          }
        },
        "pattern": [
          " A",
          "BA",
          "CC"
        ],
        "result": {
          "item": "mcwbyg:sythian_chair"
        }
      }
    }
  ]
}