{
  "type": "forge:conditional",
  "forge:condition": {
    "type": "forge:and",
    "values": [
      {
        "type": "forge:mod_loaded",
        "modid": "mcwfurnitures"
      },
      {
        "type": "forge:mod_loaded",
        "modid": "biomeswevegone"
      }
    ]
  },
  "recipes": [
    {
      "recipe": {
        "type": "minecraft:crafting_shaped",
        "category": "building",
        "group": "table",
        "key": {
          "A": {
            "item": "mcwbyg:stripped_redwood_coffee_table"
          },
          "B": {
            "item": "biomeswevegone:redwood_fence"
          }
        },
        "pattern": [
          "A",
          "B"
        ],
        "result": {
          "count": 1,
          "id": "mcwbyg:stripped_redwood_table"
        }
      }
    }
  ]
}