{
  "fabric:load_conditions": [
    {
      "condition": "fabric:all_mods_loaded",
      "values": [
        "mcwfurnitures",
        "biomesoplenty"
      ]
    }
  ],
  "type": "minecraft:crafting_shaped",
  "category": "building",
  "group": "double_drawer",
  "key": {
    "A": {
      "item": "biomesoplenty:mahogany_log"
    },
    "B": {
      "item": "mcwfurnitures:cabinet_drawer"
    }
  },
  "pattern": [
    "AAA",
    "ABA",
    "ABA"
  ],
  "result": {
    "count": 4,
    "id": "mcwbiomesoplenty:mahogany_double_drawer"
  }
}