{
  "parent": "minecraft:recipes/root",
  "rewards": {
    "recipes": [
      "mcwterraformersmc:yucca_palm_ranch_trapdoor"
    ]
  },
  "criteria": {
    "has_yucca_palm_log": {
      "trigger": "minecraft:inventory_changed",
      "conditions": {
        "items": [
          {
            "items": [
              "terrestria:yucca_palm_log"
            ]
          }
        ]
      }
    },
    "has_the_recipe": {
      "trigger": "minecraft:recipe_unlocked",
      "conditions": {
        "recipe": "mcwterraformersmc:yucca_palm_ranch_trapdoor"
      }
    }
  },
  "requirements": [
    [
      "has_yucca_palm_log",
      "has_the_recipe"
    ]
  ],
  "fabric:load_conditions": [
    {
      "condition": "fabric:all_mods_loaded",
      "values": [
        "terrestria",
        "mcwtrpdoors"
      ]
    }
  ]
}