{
  "type": "forge:conditional",
  "recipes": [
    {
      "conditions": [
        {
          "type": "forge:mod_loaded",
          "modid": "mcwdoors"
        },
        {
          "type": "forge:mod_loaded",
          "modid": "mysticsbiomes"
        }
      ],
      "recipe": {
        "type": "minecraft:crafting_shaped",
        "group": "classic",
        "key": {
          "A": {
            "item": "mysticsbiomes:strawberry_planks"
          },
          "B": {
            "item": "mcwdoors:print_oak"
          }
        },
        "pattern": [
          "A",
          "B",
          "A"
        ],
        "result": {
          "item": "mcwmysticbiomes:strawberry_classic_door"
        }
      }
    }
  ]
}