{
  "type": "forge:conditional",
  "recipes": [
    {
      "conditions": [
        {
          "type": "forge:mod_loaded",
          "modid": "mcwtrpdoors"
        },
        {
          "type": "forge:mod_loaded",
          "modid": "blue_skies"
        }
      ],
      "recipe": {
        "type": "minecraft:crafting_shaped",
        "category": "building",
        "group": "barn_trapdoors",
        "key": {
          "A": {
            "item": "blue_skies:frostbright_planks"
          },
          "B": {
            "item": "mcwmoddinglegacy:bsky_frostbright_glass_trapdoor"
          }
        },
        "pattern": [
          "A",
          "B"
        ],
        "result": {
          "item": "mcwmoddinglegacy:bsky_frostbright_barn_trapdoor"
        }
      }
    }
  ]
}