{
  "type": "forge:conditional",
  "recipes": [
    {
      "conditions": [
        {
          "type": "forge:mod_loaded",
          "modid": "mcwbridges"
        },
        {
          "type": "forge:mod_loaded",
          "modid": "caverns_and_chasms"
        }
      ],
      "recipe": {
        "type": "minecraft:stonecutting",
        "count": 1,
        "ingredient": {
          "item": "caverns_and_chasms:lapis_bricks"
        },
        "result": "mcwabnormals:lapis_bricks_bridge_pier"
      }
    }
  ]
}