{
  "type": "minecraft:crafting_shaped",
  "fabric:load_conditions": [
    {
      "condition": "fabric:all_mods_loaded",
      "values": [
        "mcwfurnitures",
        "terrestria"
      ]
    }
  ],
  "group": "chair",
  "key": {
    "A": {
      "item": "terrestria:stripped_hemlock_log"
    },
    "B": {
      "item": "terrestria:hemlock_slab"
    },
    "C": {
      "item": "terrestria:hemlock_fence"
    }
  },
  "pattern": [
    " A",
    "BA",
    "CC"
  ],
  "result": {
    "item": "mcwterraformersmc:stripped_hemlock_chair"
  }
}