{
  "advancements": [
    {
      "parent": "minecraft:recipes/root",
      "criteria": {
        "has_the_recipe": {
          "conditions": {
            "recipe": "mcwbyg:stripped_white_mangrove_table"
          },
          "trigger": "minecraft:recipe_unlocked"
        },
        "has_white_mangrove_log": {
          "conditions": {
            "items": [
              {
                "items": "biomeswevegone:white_mangrove_log"
              }
            ]
          },
          "trigger": "minecraft:inventory_changed"
        }
      },
      "forge:condition": {
        "type": "forge:and",
        "values": [
          {
            "type": "forge:mod_loaded",
            "modid": "mcwfurnitures"
          },
          {
            "type": "forge:mod_loaded",
            "modid": "biomeswevegone"
          }
        ]
      },
      "requirements": [
        [
          "has_the_recipe",
          "has_white_mangrove_log"
        ]
      ],
      "rewards": {
        "recipes": [
          "mcwbyg:stripped_white_mangrove_table"
        ]
      }
    }
  ]
}