{
  "fabric:load_conditions": [
    {
      "condition": "fabric:all_mods_loaded",
      "values": [
        "regions_unexplored",
        "mcwfurnitures"
      ]
    }
  ],
  "type": "minecraft:crafting_shaped",
  "category": "building",
  "group": "stripped_glass_kitchen_cabinets",
  "key": {
    "A": {
      "item": "regions_unexplored:stripped_kapok_log"
    },
    "B": {
      "item": "minecraft:glass"
    },
    "C": {
      "item": "mcwfurnitures:cabinet_door"
    }
  },
  "pattern": [
    "AA",
    "BC",
    "AA"
  ],
  "result": {
    "count": 4,
    "item": "mcwregionsunexplored:stripped_kapok_glass_kitchen_cabinet"
  },
  "show_notification": true
}