{
  "advancements": [
    {
      "conditions": [
        {
          "modid": "mcwbridges",
          "type": "forge:mod_loaded"
        },
        {
          "modid": "byg",
          "type": "forge:mod_loaded"
        }
      ],
      "advancement": {
        "parent": "minecraft:recipes/root",
        "rewards": {
          "recipes": [
            "mcwbyg:aspen_log_bridge_middle"
          ]
        },
        "criteria": {
          "has_item": {
            "trigger": "minecraft:inventory_changed",
            "conditions": {
              "items": [
                {
                  "item": "byg:aspen_log"
                }
              ]
            }
          },
          "has_the_recipe": {
            "trigger": "minecraft:recipe_unlocked",
            "conditions": {
              "recipe": "mcwbyg:aspen_log_bridge_middle"
            }
          }
        },
        "requirements": [
          [
            "has_item",
            "has_the_recipe"
          ]
        ]
      }
    }
  ]
}