{
  "neoforge:conditions": [
    {
      "type": "neoforge:mod_loaded",
      "modid": "mcwfurnitures"
    },
    {
      "type": "neoforge:mod_loaded",
      "modid": "biomeswevegone"
    }
  ],
  "type": "minecraft:crafting_shaped",
  "category": "building",
  "group": "kitchen_sink",
  "key": {
    "A": "biomeswevegone:stripped_witch_hazel_log",
    "B": "minecraft:water_bucket",
    "C": "biomeswevegone:witch_hazel_slab",
    "D": "minecraft:cauldron"
  },
  "pattern": [
    "CDC",
    "ABA",
    "ABA"
  ],
  "result": {
    "count": 1,
    "id": "mcwbyg:stripped_witch_hazel_kitchen_sink"
  }
}