{
  "type": "forge:conditional",
  "recipes": [
    {
      "conditions": [
        {
          "type": "forge:mod_loaded",
          "modid": "mcwfences"
        },
        {
          "type": "forge:mod_loaded",
          "modid": "terrestria"
        }
      ],
      "recipe": {
        "type": "minecraft:crafting_shaped",
        "group": "pillarwall",
        "key": {
          "A": {
            "item": "terrestria:basalt_cobblestone"
          },
          "B": {
            "item": "terrestria:basalt_bricks"
          }
        },
        "pattern": [
          "AAA",
          "B B"
        ],
        "result": {
          "count": 5,
          "item": "mcwterraformersmc:basalt_bricks_pillar_wall"
        }
      }
    }
  ]
}