{
  "type": "forge:conditional",
  "recipes": [
    {
      "conditions": [
        {
          "type": "forge:mod_loaded",
          "modid": "mcwfurnitures"
        },
        {
          "type": "forge:mod_loaded",
          "modid": "terrestria"
        }
      ],
      "recipe": {
        "type": "minecraft:crafting_shaped",
        "group": "kitchen_sinks",
        "key": {
          "A": {
            "item": "terrestria:willow_log"
          },
          "B": {
            "item": "minecraft:water_bucket"
          },
          "C": {
            "item": "terrestria:willow_slab"
          },
          "D": {
            "item": "minecraft:cauldron"
          }
        },
        "pattern": [
          "CDC",
          "ABA",
          "ABA"
        ],
        "result": {
          "item": "mcwterraformersmc:willow_kitchen_sink"
        }
      }
    }
  ]
}